{
    "Group":  "Widgets",
    "FriendlyName":  "Whatsapp",
    "SupportedVersions":  [
                              "4.70"
                          ],
    "Author":  "umitsahin",
    "DisplayOrder":  50,
    "FileName":  "Nop.Plugin.Widgets.Whatsapp.dll",
    "Description":  "This plugin contact us whatsapp",
    "LimitedToStores":  [
                            31
                        ],
    "LimitedToCustomerRoles":  [

                               ],
    "DependsOnSystemNames":  [

                             ],
    "SystemName":  "Widgets.Whatsapp",
    "Version":  "1.00"
}
